pralekh/__init__.py
pralekh/docx_handler.py
pralekh/extractor.py
pralekh/pdf_handler.py
pralekh/pptx_handler.py
pralekh/txt_handler.py
pralekh/xlsx_handler.py
pralekh-0.1.0.dist-info/METADATA
pralekh-0.1.0.dist-info/WHEEL
pralekh-0.1.0.dist-info/top_level.txt
pralekh-0.1.0.dist-info/RECORD
